Metadata-Version: 1.1
Name: artifactory
Version: 0.1.17
Summary: A Python to Artifactory interface
Home-page: http://github.com/parallels/artifactory
Author: Konstantin Nazarov
Author-email: knazarov@parallels.com
License: MIT License
Download-URL: http://github.com/parallels/artifactory
Platform: UNKNOWN
Classifier: Development Status :: 3 - Alpha
Classifier: Intended Audience :: Developers
Classifier: License :: OSI Approved :: MIT License
Classifier: Operating System :: OS Independent
Classifier: Programming Language :: Python :: 3
Classifier: Programming Language :: Python :: 2.7
Classifier: Programming Language :: Python :: 3.2
Classifier: Programming Language :: Python :: 3.3
Classifier: Topic :: Software Development :: Libraries
Classifier: Topic :: System :: Filesystems
